bin/cuerunbase.py
bin/pycuerun
bin/util_qc_job_layer.py
outline/__init__.py
outline/config.py
outline/constants.py
outline/cuerun.py
outline/depend.py
outline/event.py
outline/exception.py
outline/executor.py
outline/io.py
outline/layer.py
outline/loader.py
outline/outline.cfg
outline/session.py
outline/util.py
outline/backend/__init__.py
outline/backend/cue.py
outline/backend/local.py
outline/modules/__init__.py
outline/modules/shell.py
outline/plugins/__init__.py
outline/plugins/local.py
outline/plugins/manager.py
outline/versions/__init__.py
outline/versions/main.py
outline/versions/session.py
wrappers/local_wrap_frame
wrappers/opencue_wrap_frame
wrappers/opencue_wrap_frame_no_ss
opencue_pyoutline-1.13.8.dist-info/METADATA
opencue_pyoutline-1.13.8.dist-info/WHEEL
opencue_pyoutline-1.13.8.dist-info/RECORD
