Metadata-Version: 2.1
Name: opencue_pyoutline
Version: 1.13.8
Summary: PyOutline is a Python library for building and managing OpenCue job definitions. It provides an API to create outlines that describe jobs, layers, and tasks, making it easier to construct repeatable workflows for rendering pipelines.
Requires-Python: >3.7
Requires-Dist: opencue-pycue
Provides-Extra: test
Requires-Dist: mock==2.0.0; extra == 'test'
Requires-Dist: pyfakefs==5.2.3; extra == 'test'
Requires-Dist: pytest; extra == 'test'
